datatrove/__init__.py
datatrove/data.py
datatrove/io.py
datatrove/assets/banned_subwords.txt
datatrove/assets/banned_words.txt
datatrove/assets/soft_banned_words.txt
datatrove/assets/tokenizer_assignment.csv
datatrove/assets/url_filterblacklistsv0_3_0.tar.gz
datatrove/executor/__init__.py
datatrove/executor/base.py
datatrove/executor/local.py
datatrove/executor/ray.py
datatrove/executor/slurm.py
datatrove/pipeline/__init__.py
datatrove/pipeline/base.py
datatrove/pipeline/decont/__init__.py
datatrove/pipeline/decont/n_grams.py
datatrove/pipeline/dedup/__init__.py
datatrove/pipeline/dedup/bloom_filter.py
datatrove/pipeline/dedup/exact_dedup.py
datatrove/pipeline/dedup/exact_substrings.py
datatrove/pipeline/dedup/minhash.py
datatrove/pipeline/dedup/sentence_dedup.py
datatrove/pipeline/extractors/__init__.py
datatrove/pipeline/extractors/base.py
datatrove/pipeline/extractors/modular.py
datatrove/pipeline/extractors/trafilatura.py
datatrove/pipeline/filters/__init__.py
datatrove/pipeline/filters/base_filter.py
datatrove/pipeline/filters/c4_filters.py
datatrove/pipeline/filters/fasttext_filter.py
datatrove/pipeline/filters/fineweb_quality_filter.py
datatrove/pipeline/filters/gopher_quality_filter.py
datatrove/pipeline/filters/gopher_repetition_filter.py
datatrove/pipeline/filters/lambda_filter.py
datatrove/pipeline/filters/language_filter.py
datatrove/pipeline/filters/regex_filter.py
datatrove/pipeline/filters/sampler_filter.py
datatrove/pipeline/filters/unigram_log_probs.py
datatrove/pipeline/filters/url_filter.py
datatrove/pipeline/formatters/__init__.py
datatrove/pipeline/formatters/base.py
datatrove/pipeline/formatters/ftfy.py
datatrove/pipeline/formatters/pii.py
datatrove/pipeline/formatters/symbol_lines_remover.py
datatrove/pipeline/inference/__init__.py
datatrove/pipeline/inference/checkpointing.py
datatrove/pipeline/inference/dataset_card_generator.py
datatrove/pipeline/inference/metrics.py
datatrove/pipeline/inference/progress_monitor.py
datatrove-0.8.0.dist-info/licenses/LICENSE
datatrove-0.8.0.dist-info/METADATA
datatrove-0.8.0.dist-info/WHEEL
datatrove-0.8.0.dist-info/entry_points.txt
datatrove-0.8.0.dist-info/top_level.txt
datatrove-0.8.0.dist-info/RECORD
