Metadata-Version: 2.4
Name: datatrove
Version: 0.8.0
Summary: HuggingFace library to process and filter large amounts of webdata
Author-email: "HuggingFace Inc." <guilherme@macrodata.co>
License: Apache-2.0
Project-URL: Repository, https://github.com/huggingface/datatrove
Keywords: data,machine,learning,processing
Classifier: Intended Audience :: Developers
Classifier: Intended Audience :: Education
Classifier: Intended Audience :: Science/Research
Classifier: License :: OSI Approved :: Apache Software License
Classifier: Operating System :: OS Independent
Classifier: Programming Language :: Python :: 3
Classifier: Programming Language :: Python :: 3.10
Classifier: Programming Language :: Python :: 3.11
Classifier: Programming Language :: Python :: 3.12
Classifier: Topic :: Scientific/Engineering :: Artificial Intelligence
Requires-Python: >=3.10.0
License-File: LICENSE
Requires-Dist: dill>=0.3.0
Requires-Dist: fsspec>=2023.12.2
Requires-Dist: huggingface-hub>=0.17.0
Requires-Dist: humanize
Requires-Dist: loguru>=0.7.0
Requires-Dist: multiprocess
Requires-Dist: numpy>=2.0.0
Requires-Dist: tqdm
Provides-Extra: cli
Requires-Dist: rich; extra == "cli"
Provides-Extra: io
Requires-Dist: faust-cchardet; extra == "io"
Requires-Dist: pyarrow; extra == "io"
Requires-Dist: python-magic; extra == "io"
Requires-Dist: warcio; extra == "io"
Requires-Dist: datasets>=3.1.0; extra == "io"
Requires-Dist: orjson; extra == "io"
Requires-Dist: zstandard; extra == "io"
Provides-Extra: s3
Requires-Dist: s3fs>=2023.12.2; extra == "s3"
Provides-Extra: processing
Requires-Dist: fasttext-numpy2-wheel; extra == "processing"
Requires-Dist: nltk; extra == "processing"
Requires-Dist: inscriptis; extra == "processing"
Requires-Dist: tldextract; extra == "processing"
Requires-Dist: trafilatura<1.12.0,>=1.8.0; extra == "processing"
Requires-Dist: tokenizers; extra == "processing"
Requires-Dist: ftfy; extra == "processing"
Requires-Dist: fasteners; extra == "processing"
Requires-Dist: regex; extra == "processing"
Requires-Dist: xxhash; extra == "processing"
Requires-Dist: pyahocorasick; extra == "processing"
Provides-Extra: decont
Requires-Dist: lighteval>=0.3.0; extra == "decont"
Provides-Extra: multilingual
Requires-Dist: spacy[ja]>=3.8; extra == "multilingual"
Requires-Dist: stanza; extra == "multilingual"
Requires-Dist: pyvi; extra == "multilingual"
Requires-Dist: pythainlp; extra == "multilingual"
Requires-Dist: jieba; extra == "multilingual"
Requires-Dist: indic-nlp-library; extra == "multilingual"
Requires-Dist: kiwipiepy<0.22.0; extra == "multilingual"
Requires-Dist: urduhack; extra == "multilingual"
Requires-Dist: tensorflow>=2.16; extra == "multilingual"
Requires-Dist: khmer-nltk; extra == "multilingual"
Requires-Dist: laonlp; extra == "multilingual"
Requires-Dist: botok; extra == "multilingual"
Requires-Dist: pyidaungsu-numpy2; extra == "multilingual"
Provides-Extra: inference
Requires-Dist: aiofiles; extra == "inference"
Requires-Dist: orjson; extra == "inference"
Requires-Dist: httpx; extra == "inference"
Requires-Dist: aiosqlite; extra == "inference"
Requires-Dist: typer; extra == "inference"
Requires-Dist: pyyaml; extra == "inference"
Requires-Dist: pandas; extra == "inference"
Provides-Extra: ray
Requires-Dist: ray[default]; extra == "ray"
Provides-Extra: quality
Requires-Dist: ruff>=0.1.5; extra == "quality"
Provides-Extra: testing
Requires-Dist: datatrove[cli]; extra == "testing"
Requires-Dist: datatrove[io]; extra == "testing"
Requires-Dist: datatrove[processing]; extra == "testing"
Requires-Dist: datatrove[multilingual]; extra == "testing"
Requires-Dist: datatrove[s3]; extra == "testing"
Requires-Dist: datatrove[ray]; extra == "testing"
Requires-Dist: datatrove[inference]; extra == "testing"
Requires-Dist: flask>=3.1.0; extra == "testing"
Requires-Dist: pytest; extra == "testing"
Requires-Dist: pytest-rerunfailures; extra == "testing"
Requires-Dist: pytest-timeout; extra == "testing"
Requires-Dist: pytest-xdist; extra == "testing"
Requires-Dist: moto[s3,server]; extra == "testing"
Requires-Dist: spacy[ja]; extra == "testing"
Provides-Extra: all
Requires-Dist: datatrove[quality]; extra == "all"
Requires-Dist: datatrove[testing]; extra == "all"
Provides-Extra: dev
Requires-Dist: datatrove[all]; extra == "dev"
Dynamic: license-file
